jax_tvm_ffi-0.1.1.dist-info/RECORD
jax_tvm_ffi-0.1.1.dist-info/WHEEL
jax_tvm_ffi-0.1.1.dist-info/METADATA
jax_tvm_ffi-0.1.1.dist-info/licenses/LICENSE
jax_tvm_ffi-0.1.1.dist-info/licenses/NOTICE
jax_tvm_ffi/jax_tvm_ffi.dylib
jax_tvm_ffi/__init__.py
