Metadata-Version: 2.1
Name: jax-tvm-ffi
Version: 0.1.1
Keywords: machine learning,inference
License: Apache 2.0
Classifier: License :: OSI Approved :: Apache Software License
Classifier: Development Status :: 4 - Beta
Classifier: Intended Audience :: Developers
Classifier: Intended Audience :: Education
Classifier: Intended Audience :: Science/Research
Requires-Python: >=3.11
Requires-Dist: jax>=0.7.2
Requires-Dist: apache-tvm-ffi>=0.1.0
